fastdeploy_llm/__init__.py
fastdeploy_llm/config.py
fastdeploy_llm/engine.py
fastdeploy_llm/model.py
fastdeploy_llm/processor.py
fastdeploy_llm/task.py
fastdeploy_llm/client/__init__.py
fastdeploy_llm/client/grpc_client.py
fastdeploy_llm/serving/__init__.py
fastdeploy_llm/serving/serving_model.py
fastdeploy_llm/serving/triton_model.py
fastdeploy_llm/serving/triton_template.py
fastdeploy_llm/utils/__init__.py
fastdeploy_llm/utils/launch_infer.py
fastdeploy_llm/utils/logging_util.py
fastdeploy_llm/utils/prefix_utils.py
fastdeploy_llm/utils/utils.py
fastdeploy_llm-0.0.8.dist-info/METADATA
fastdeploy_llm-0.0.8.dist-info/WHEEL
fastdeploy_llm-0.0.8.dist-info/top_level.txt
fastdeploy_llm-0.0.8.dist-info/RECORD
