Metadata-Version: 2.1
Name: fastdeploy-llm
Version: 0.0.8
Summary: FastDeploy for Large Language Model
Home-page: https://github.com/PaddlePaddle/FastDeploy
Author: fastdeploy
Author-email: fastdeploy@baidu.com
License: Apache 2.0
Classifier: Programming Language :: Python :: 3
Classifier: License :: OSI Approved :: Apache Software License
Classifier: Operating System :: OS Independent
Requires-Dist: colorlog
Provides-Extra: client
Requires-Dist: grpcio ; extra == 'client'
Requires-Dist: tritonclient ; extra == 'client'
